opcodes.vh
// Modos de direccionamiento (addressing) (son parte del opcode [7:0], específicamente los bits [2:0])
`define DIRECC_IMP    'b000  // Direccionamiento implícito o no necesario para la operación
`define DIRECC_INM    'b001  // Direccionamiento inmediato
`define DIRECC_REG    'b010  // Direccionamiento de registros
`define DIRECC_DIRECT 'b011  // Direccionamiento directo
`define DIRECC_INDREG 'b100  // Direccionamiento indirecto por registros

// Opcodes

// Opcodes especiales
`define OP_NOP        'b00000  // (0x00) Ningúna Operación (hace nada, No Op)
`define OP_HLT        'b11111  // (0x1F) Halt. Detiene la máquina/CPU
// Memoria
`define OP_LD         'b00001  // (0x01)
`define OP_STR        'b00010  // (0x02)
// Lógicas
`define OP_NOT        'b10000  // (0x10)
`define OP_AND        'b10001  // (0x11)
`define OP_OR         'b10010  // (0x12)
`define OP_XOR        'b10011  // (0x13)
// Aritméticas
`define OP_NEG        'b10100  // (0x14)
`define OP_ADD        'b10101  // (0x15)
`define OP_SUB        'b10110  // (0x16)
`define OP_MUL        'b10111  // (0x17)
`define OP_DIV        'b11000  // (0x18)
`define OP_MOD        'b11001  // (0x19)
// Control
`define OP_JMP        'b11010  // (0x1A)
`define OP_JC         'b11011  // (0x1B)
`define OP_JS         'b11100  // (0x1C)
`define OP_JO         'b11101  // (0x1D)
`define OP_JZ         'b11110  // (0x1E)

// Combinaciones válidas de Opcodes y Direccionamiento

// Opcodes especiales
`define OPD_NOP        'b00000_000  // (0x00) Ningúna Operación (hace nada, No Op)
`define OPD_HLT        'b11111_000  // (0xF8) Halt. Detiene la máquina/CPU
// Memoria
// (Para el load, el destino siempre es un registro. La fuente puede variar dependiendo del modo de direccionamiento)
`define OPD_LD_INM     'b00001_001  // (0x09) Carga un valor inmediato al registro. Ya que el valor inmediato son 16 bits y el registro 32 bits, se hará extensión de signo
`define OPD_LD_REG     'b00001_010  // (0x0A) Load entre registros. Permite mover fácilmente el valor de un Registro A a otro Registro B
`define OPD_LD_DIRECT  'b00001_011  // (0x0B)
`define OPD_LD_INDREG  'b00001_100  // (0x0C)
// (Para el store, la fuente siempre es un registro. El destino puede variar dependiendo del modo de direccionamiento)
`define OPD_STR_DIRECT 'b00010_011  // (0x13)
`define OPD_STR_INDREG 'b00010_100  // (0x14)
// Lógicas (Todas usa direccionamiento de registros únicamente)
`define OPD_NOT        'b10000_010  // (0x82)
`define OPD_AND        'b10001_010  // (0x86)
`define OPD_OR         'b10010_010  // (0x92)
`define OPD_XOR        'b10011_010  // (0x96)
// Aritméticas (Todas usa direccionamiento de registros únicamente)
`define OPD_NEG        'b10100_010  // (0xA2)
`define OPD_ADD        'b10101_010  // (0xA6)
`define OPD_SUB        'b10110_010  // (0xB2)
`define OPD_MUL        'b10111_010  // (0xB6)
`define OPD_DIV        'b11000_010  // (0xC2)
`define OPD_MOD        'b11001_010  // (0xC6)
// Control (Todas son saltos absolutos, y usan direccionamiento inmediato únicamente)
`define OPD_JMP        'b11010_001  // (0xD1)
`define OPD_JC         'b11011_001  // (0xD9)
`define OPD_JS         'b11100_001  // (0xE1)
`define OPD_JO         'b11101_001  // (0xE9)
`define OPD_JZ         'b11110_001  // (0xF1)

// Para ver los opcodes con nombres en GTKWave
// https://electronics.stackexchange.com/questions/530123/viewing-verilog-enums-in-iverilog-gtkwave

// Create a file with the extension gtkw. This file contains how you want the state variable to be displayed on
// the waveform. For your example it would be:
//
// 00 STATE0
// 01 STATE1
// 10 STATE2
//
// Because you have used logic type which is 2 bits wide and have not encoded the state variables, SystemVerilog
// assigns the state variables the default values in ascending order. In this case the default binary values would
// be from 00 to 10 since you have 3 State variables.
// 
// Open the waveform and dump the signal. Do  Right-Mouse -> Data Format -> Translate Filter File -> Enable and Select.
// The Select Signal Filter Dialog Box opens. Then left click on Add Filter to List button. Select the gtkw extension file
// that you created. This file will then be displayed in the Select Signal Filter dialog box. Select your file in the Select
// Filter Dialog Box, make sure it is highlighted, then left click on the OK button. The binary signals in the waveform should
// be replaced with the enum values.

alu.v
/*******************************
Universidad de Costa Rica
CI-0114: Fundamentos de Arquitectura

Modulo de una ALU combinacional,
parcialmente implementada

*********************************/

`include "opcodes.vh"

module ALU(resultado, C, S, O, Z, operando_a, operando_b, opcode);
  parameter BITS_DATA = 32;

  output reg [BITS_DATA-1:0] resultado;
  output reg C;
  output reg S;
  output reg O;
  output reg Z;

  input [BITS_DATA-1:0] operando_a;
  input [BITS_DATA-1:0] operando_b;
  input [4:0] opcode;
  
  // Con el @*, estamos definiendo un bloque combinacional
  // ya que no depende de ningún reloj
  // La lógica combinacional debe usar asignación bloqueante
  always @* begin
    case (opcode)
      `OP_NOT: begin
        resultado = ~operando_a;
        C = 0;
        S = resultado[BITS_DATA-1];
        O = 0;
        Z = ~(|resultado);
      end

      `OP_ADD: begin
        {C,resultado} = operando_a + operando_b;
        S = resultado[BITS_DATA-1];
        // Overflow es 1 cuando hay cambio en el bit de signo. Solo
        // puedo ocurrir cuando los operandos tienen el mismo signo
        O = (operando_a[BITS_DATA-1] == operando_b[BITS_DATA-1]) &&
            (operando_a[BITS_DATA-1] !=  resultado[BITS_DATA-1]);
        Z = ~(|resultado);
      end

      default: begin
        // El opcode no esta implementado o bien no es un
        // opcode de ALU valido. Intencionalmente propagaremos
        // Xs (indeterminado) a las salidas 
        resultado = 'hXXXX_XXXX;
        C = 'bx;
        S = 'bx;
        O = 'bx;
        Z = 'bx;
      end
    endcase
  end

endmodule

alu_tb.v
/*******************************
Universidad de Costa Rica
CI-0114: Fundamentos de Arquitectura

Prueba para la ALU

Archibald Emmanuel Carrion Claeys
C01736
iverilog alu.v alu_tb.v
*********************************/

`timescale 1us/100ns

module ALU_tb;
  wire [31:0] R;
  wire C, S, O, Z;
  reg  [31:0] A;
  reg  [31:0] B;
  reg  [4:0]  op;
 
  initial begin
    $dumpfile("alu.vcd");
    $dumpvars;
	$monitor("\n opcode : %b \n Output : %b \n C flag : %b \n S flag : %b \n O flag : %b \n Z flag : %b \n A Operand : %b \n B Operand : %b \n\n##############################################", op, R, C, S, O , Z, A, B);
	
	
	
    #1 op = `OP_NOP; A = 0; B = 0;
	
	#1 op = `OP_NOT; A = 32'h0000_FFFF;
	#1 op = `OP_NOT; A = 32'hFFFF_FFFF;
	#1 op = `OP_NOT; A = 32'h0000_0000;
	#1 op = `OP_NOT; A = 32'h7777_7777;
	#1 op = `OP_NOT; A = 32'hF000_FFFF;
	
    
	
	#1 op = `OP_AND; A = 32'h0000_1111; B = 32'h1010_0011;
	#1 op = `OP_AND; A = 32'h0000_1111; B = 32'h1010_0011;
	#1 op = `OP_AND; A = 32'h0000_1111; B = 32'h1010_0011;
	#1 op = `OP_AND; A = 32'h0000_1111; B = 32'h1010_0011;
	#1 op = `OP_AND; A = 32'h0000_1111; B = 32'h1010_0011;
	
    //#1 op = `OP_NOT; A = 32'hACED_CAFE; B = 32'hXXXX_XXXX;
	#1 op = `OP_OR; A = 32'hFFFF_FFFF; B = 32'hFFFF_FFFF;
	#1 op = `OP_OR; A = 32'h0000_0000; B = 32'h0000_0000;
	#1 op = `OP_OR; A = 32'hFFFF_0000; B = 32'h0000_FFFF;
	#1 op = `OP_OR; A = 32'h0000_7777; B = 32'h0000_0000;
	#1 op = `OP_OR; A = 32'h0000_0001; B = 32'h0000_0001;
	
	#1 op = `OP_NEG; A = 32'hFFFF_FFFF;
	#1 op = `OP_NEG; A = 32'h0000_0000;
	#1 op = `OP_NEG; A = 32'h0000_5555;
	#1 op = `OP_NEG; A = 32'hF0F0_F0F0;
	#1 op = `OP_NEG; A = 32'h0F0F_0F0F;
	
	#1 op = `OP_ADD; A = 32'h8000_0000; B = 32'h8000_0000;
    #1 op = `OP_ADD; A = 32'hFFFF_0000; B = 32'hFFFF_FFFF;
    #1 op = `OP_ADD; A = 32'hFFFF_0000; B = 32'h0FFF_1111;
    #1 op = `OP_ADD; A = 32'h7FFF_0000; B = 32'h7FFF_1111;
    #1 op = `OP_ADD; A = 32'h7FFF_0000; B = 32'h0FFF_1111;
	
	#1 op = `OP_SUB; A = 32'hFFFF_FFFF; B = 32'h0000_0001;
	#1 op = `OP_SUB; A = 32'hFFFF_FFFF; B = 32'hFFFF_FFFF;
	#1 op = `OP_SUB; A = 32'h0000_FFFF; B = 32'h0000_FFFF;
	#1 op = `OP_SUB; A = 32'h0505_0505; B = 32'h0505_0505;
	#1 op = `OP_SUB; A = 32'h0000_0000; B = 32'h0000_0001;
	
	#1 op = `OP_NOP; A = 0; B = 0;
	#1 op = `OP_HLT;
	
	
	
	//`OP_NOP
			
			//`OP_HLT
			
			//`OP_NOT
			
			//`OP_AND
			
			//`OP_OR
			
			//`OP_NEG

			//`OP_ADD
			
			//`OP_SUB
				

    #1 $finish;
  end
  
  ALU alu(.resultado(R), .C(C), .S(S), .O(O), .Z(Z), .operando_a(A), .operando_b(B), .opcode(op));
		  

endmodule

ALU.vcd
$date
	Thu Jun 16 11:25:30 2022
$end
$version
	Icarus Verilog
$end
$timescale
	100ns
$end
$scope module ALU_tb $end
$var wire 1 ! Z $end
$var wire 1 " S $end
$var wire 32 # R [31:0] $end
$var wire 1 $ O $end
$var wire 1 % C $end
$var reg 32 & A [31:0] $end
$var reg 32 ' B [31:0] $end
$var reg 5 ( op [4:0] $end
$scope module alu $end
$var wire 5 ) opcode [4:0] $end
$var wire 32 * operando_a [31:0] $end
$var wire 32 + operando_b [31:0] $end
$var reg 1 % C $end
$var reg 1 $ O $end
$var reg 1 " S $end
$var reg 1 ! Z $end
$var reg 32 , resultado [31:0] $end
$upscope $end
$upscope $end
$enddefinitions $end
#0
$dumpvars
bx ,
bx +
bx *
bx )
bx (
bx '
bx &
x%
x$
bx #
x"
x!
$end
#10
b0 '
b0 +
b0 &
b0 *
b0 (
b0 )
#20
0!
0$
1"
0%
b11111111111111110000000000000000 #
b11111111111111110000000000000000 ,
b1111111111111111 &
b1111111111111111 *
b10000 (
b10000 )
#30
1!
0"
b0 #
b0 ,
b11111111111111111111111111111111 &
b11111111111111111111111111111111 *
#40
0!
1"
b11111111111111111111111111111111 #
b11111111111111111111111111111111 ,
b0 &
b0 *
#50
b10001000100010001000100010001000 #
b10001000100010001000100010001000 ,
b1110111011101110111011101110111 &
b1110111011101110111011101110111 *
#60
0"
b1111111111110000000000000000 #
b1111111111110000000000000000 ,
b11110000000000001111111111111111 &
b11110000000000001111111111111111 *
#70
b10001 #
b10001 ,
b10000000100000000000000010001 '
b10000000100000000000000010001 +
b1000100010001 &
b1000100010001 *
b10001 (
b10001 )
#120
1"
b11111111111111111111111111111111 #
b11111111111111111111111111111111 ,
b11111111111111111111111111111111 '
b11111111111111111111111111111111 +
b11111111111111111111111111111111 &
b11111111111111111111111111111111 *
b10010 (
b10010 )
#130
1!
0"
b0 #
b0 ,
b0 '
b0 +
b0 &
b0 *
#140
0!
1"
b11111111111111111111111111111111 #
b11111111111111111111111111111111 ,
b1111111111111111 '
b1111111111111111 +
b11111111111111110000000000000000 &
b11111111111111110000000000000000 *
#150
0"
b111011101110111 #
b111011101110111 ,
b0 '
b0 +
b111011101110111 &
b111011101110111 *
#160
b1 #
b1 ,
b1 '
b1 +
b1 &
b1 *
#170
b11111111111111111111111111111111 &
b11111111111111111111111111111111 *
b10100 (
b10100 )
#180
1!
b0 #
b0 ,
b0 &
b0 *
#190
0!
1"
b11111111111111111010101010101011 #
b11111111111111111010101010101011 ,
b101010101010101 &
b101010101010101 *
#200
0"
b1111000011110000111100010000 #
b1111000011110000111100010000 ,
b11110000111100001111000011110000 &
b11110000111100001111000011110000 *
#210
1"
b11110000111100001111000011110001 #
b11110000111100001111000011110001 ,
b1111000011110000111100001111 &
b1111000011110000111100001111 *
#220
1!
1$
0"
1%
b0 #
b0 ,
b10000000000000000000000000000000 '
b10000000000000000000000000000000 +
b10000000000000000000000000000000 &
b10000000000000000000000000000000 *
b10101 (
b10101 )
#230
0!
0$
1"
b11111111111111101111111111111111 #
b11111111111111101111111111111111 ,
b11111111111111111111111111111111 '
b11111111111111111111111111111111 +
b11111111111111110000000000000000 &
b11111111111111110000000000000000 *
#240
0"
b1111111111100001000100010001 #
b1111111111100001000100010001 ,
b1111111111110001000100010001 '
b1111111111110001000100010001 +
#250
1$
1"
0%
b11111111111111100001000100010001 #
b11111111111111100001000100010001 ,
b1111111111111110001000100010001 '
b1111111111111110001000100010001 +
b1111111111111110000000000000000 &
b1111111111111110000000000000000 *
#260
b10001111111111100001000100010001 #
b10001111111111100001000100010001 ,
b1111111111110001000100010001 '
b1111111111110001000100010001 +
#270
0$
b11111111111111111111111111111110 #
b11111111111111111111111111111110 ,
b1 '
b1 +
b11111111111111111111111111111111 &
b11111111111111111111111111111111 *
b10110 (
b10110 )
#280
1!
1$
0"
b0 #
b0 ,
b11111111111111111111111111111111 '
b11111111111111111111111111111111 +
#290
0$
b1111111111111111 '
b1111111111111111 +
b1111111111111111 &
b1111111111111111 *
#300
b101000001010000010100000101 '
b101000001010000010100000101 +
b101000001010000010100000101 &
b101000001010000010100000101 *
#310
0!
1$
1"
1%
b11111111111111111111111111111111 #
b11111111111111111111111111111111 ,
b1 '
b1 +
b0 &
b0 *
#320
x!
x$
x"
x%
bx #
bx ,
b0 '
b0 +
b0 (
b0 )
#330
b11111 (
b11111 )
