memoria.v
/*******************************
Universidad de Costa Rica
CI-0114: Fundamentos de Arquitectura

Simple memoria lectura asincrónica y escritura sincrónica
basada en Flip Flops
1 Puerto de lectura
1 Puerto de escritura

Ancho de palabra (Datos) 32 bits
Ancho de direcciones 16 bits (64Ki Words)

Contiene las primeras words precargadas
Con algunos valores de prueba

*********************************/

module Mem_D32b_A16b(data_out, data_in, address, write, clk);
  parameter BITS_DATA = 32;
  parameter BITS_ADDR = 16;

  output [BITS_DATA-1:0] data_out;
  input  [BITS_DATA-1:0] data_in;
  input  [BITS_ADDR-1:0] address;
  input                  write;
  input                  clk;
  
  reg [BITS_DATA-1:0] data [(2**BITS_ADDR)-1:0];
  
  assign data_out = data[address];
  
  always @(negedge clk) begin
    if (write) begin
      data[address] <= data_in;
    end
  end
  
  // Para leer/escribir archivos de texto como memorias en verilog (nos permite una inicialización más flexible)
  // https://stackoverflow.com/questions/628603/what-is-the-function-of-readmemh-and-writememh-in-verilog
  // Otro tutorial: https://www.fullchipdesign.com/readmemh.htm
  //
  // De momento, los datos se inicializan manualmente
  initial begin    
    //data[0] = 'h00000000;
	  //data[0] = 'hFFFFFFFF; //el estado HLT funciona correctamente
	  data[0] = 'h0000FFFF;
    //00001001 xxxxx000
    data[1] = 'h01005555;
    data[2] = 'h33331111;
	  data[3] = 'hFFFFFFFF;
    //data[3] = 'h00000000;
    //data[4] = 'h00000000;
    //data[5] = 'hF8000000;
  end
  
  // Workaround para lograr visualizar la memoria en gtkwave
  // Agregamos solo los primeros 64 entries para no hacer la simulación
  // innecesariamente lenta
  generate
    genvar idx;
    for(idx = 0; idx < 64; idx = idx + 1) begin: register
      wire [31:0] tmp;
      assign tmp = data[idx];
    end
  endgenerate

endmodule

opcodes.vh
// Modos de direccionamiento (addressing) (son parte del opcode [7:0], específicamente los bits [2:0])
`define DIRECC_IMP    'b000  // Direccionamiento implícito o no necesario para la operación
`define DIRECC_INM    'b001  // Direccionamiento inmediato
`define DIRECC_REG    'b010  // Direccionamiento de registros
`define DIRECC_DIRECT 'b011  // Direccionamiento directo
`define DIRECC_INDREG 'b100  // Direccionamiento indirecto por registros

// Opcodes

// Opcodes especiales
`define OP_NOP        'b00000  // (0x00) Ningúna Operación (hace nada, No Op)
`define OP_HLT        'b11111  // (0x1F) Halt. Detiene la máquina/CPU
// Memoria
`define OP_LD         'b00001  // (0x01)
`define OP_STR        'b00010  // (0x02)
// Lógicas
`define OP_NOT        'b10000  // (0x10)
`define OP_AND        'b10001  // (0x11)
`define OP_OR         'b10010  // (0x12)
`define OP_XOR        'b10011  // (0x13)
// Aritméticas
`define OP_NEG        'b10100  // (0x14)
`define OP_ADD        'b10101  // (0x15)
`define OP_SUB        'b10110  // (0x16)
`define OP_MUL        'b10111  // (0x17)
`define OP_DIV        'b11000  // (0x18)
`define OP_MOD        'b11001  // (0x19)
// Control
`define OP_JMP        'b11010  // (0x1A)
`define OP_JC         'b11011  // (0x1B)
`define OP_JS         'b11100  // (0x1C)
`define OP_JO         'b11101  // (0x1D)
`define OP_JZ         'b11110  // (0x1E)

// Combinaciones válidas de Opcodes y Direccionamiento

// Opcodes especiales
`define OPD_NOP        'b00000_000  // (0x00) Ningúna Operación (hace nada, No Op)
`define OPD_HLT        'b11111_000  // (0xF8) Halt. Detiene la máquina/CPU
// Memoria
// (Para el load, el destino siempre es un registro. La fuente puede variar dependiendo del modo de direccionamiento)
`define OPD_LD_INM     'b00001_001  // (0x09) Carga un valor inmediato al registro. Ya que el valor inmediato son 16 bits y el registro 32 bits, se hará extensión de signo
`define OPD_LD_REG     'b00001_010  // (0x0A) Load entre registros. Permite mover fácilmente el valor de un Registro A a otro Registro B
`define OPD_LD_DIRECT  'b00001_011  // (0x0B)
`define OPD_LD_INDREG  'b00001_100  // (0x0C)
// (Para el store, la fuente siempre es un registro. El destino puede variar dependiendo del modo de direccionamiento)
`define OPD_STR_DIRECT 'b00010_011  // (0x13)
`define OPD_STR_INDREG 'b00010_100  // (0x14)
// Lógicas (Todas usa direccionamiento de registros únicamente)
`define OPD_NOT        'b10000_010  // (0x82)
`define OPD_AND        'b10001_010  // (0x86)
`define OPD_OR         'b10010_010  // (0x92)
`define OPD_XOR        'b10011_010  // (0x96)
// Aritméticas (Todas usa direccionamiento de registros únicamente)
`define OPD_NEG        'b10100_010  // (0xA2)
`define OPD_ADD        'b10101_010  // (0xA6)
`define OPD_SUB        'b10110_010  // (0xB2)
`define OPD_MUL        'b10111_010  // (0xB6)
`define OPD_DIV        'b11000_010  // (0xC2)
`define OPD_MOD        'b11001_010  // (0xC6)
// Control (Todas son saltos absolutos, y usan direccionamiento inmediato únicamente)
`define OPD_JMP        'b11010_001  // (0xD1)
`define OPD_JC         'b11011_001  // (0xD9)
`define OPD_JS         'b11100_001  // (0xE1)
`define OPD_JO         'b11101_001  // (0xE9)
`define OPD_JZ         'b11110_001  // (0xF1)

// Para ver los opcodes con nombres en GTKWave
// https://electronics.stackexchange.com/questions/530123/viewing-verilog-enums-in-iverilog-gtkwave

// Create a file with the extension gtkw. This file contains how you want the state variable to be displayed on
// the waveform. For your example it would be:
//
// 00 STATE0
// 01 STATE1
// 10 STATE2
//
// Because you have used logic type which is 2 bits wide and have not encoded the state variables, SystemVerilog
// assigns the state variables the default values in ascending order. In this case the default binary values would
// be from 00 to 10 since you have 3 State variables.
// 
// Open the waveform and dump the signal. Do  Right-Mouse -> Data Format -> Translate Filter File -> Enable and Select.
// The Select Signal Filter Dialog Box opens. Then left click on Add Filter to List button. Select the gtkw extension file
// that you created. This file will then be displayed in the Select Signal Filter dialog box. Select your file in the Select
// Filter Dialog Box, make sure it is highlighted, then left click on the OK button. The binary signals in the waveform should
// be replaced with the enum values.

registros.v
/*******************************
Universidad de Costa Rica
CI-0114: Fundamentos de Arquitectura

Circuito simple de registro que permite almacenar 32 bits

iverilog registros.v registros_tb.v
*****************************/

module registersArray(inputData, dirrInput, dirrOutput1, dirrOutput2, outputData1, outputData2, write_en, clk);
	parameter BITS_DATA = 32;								//tamano de los registros
	parameter BITS_ADDR = 3;								//tamano de las dirreciones
	
	input [BITS_DATA-1:0] inputData;						//data que hay que agregar en uno de los registros
	input [BITS_ADDR-1:0] dirrInput;						//posicion donde hay que agregar el data inputData
	input [BITS_ADDR-1:0] dirrOutput1;						//posicion del elemento que se quiere sacar de la lista de registros y se guarda en outputData1
	input [BITS_ADDR-1:0] dirrOutput2;						//posicion del elemento que se quiere sacar de la lista de registros y se guarda en outputData2
	input write_en;											// abreviado para "write enable", si esta en 1 permite cambiar el contenido de los registros, sino no puede
	input clk;												//signal del reloj
	output reg [BITS_DATA-1:0] outputData1;					//data sacado del array de registros
	output reg [BITS_DATA-1:0] outputData2;					//data sacado del array de registros
	
	reg [BITS_DATA-1:0] registersArray [7:0];				// un array de 8 array de 32 bits
	
	always @(negedge clk) begin
		if (write_en) begin
		  registersArray[dirrInput] <= inputData;
		end
	end
	
	always @(posedge clk or dirrOutput1) begin
		outputData1 <= registersArray[dirrOutput1];
	end
	
	always @(posedge clk or dirrOutput2) begin
		outputData2 <= registersArray[dirrOutput2];
	end
endmodule

alu.v
/***********************************************************
Universidad de Costa Rica
CI-0114: Fundamentos de Arquitectura

Archibald Emmanuel Carrion Claeys
C01736
Modulo de una ALU combinacional, completamente implementada
************************************************************/

`include "opcodes.vh"

module ALU(resultado, C, S, O, Z, operando_a, operando_b, opcode);
	parameter BITS_DATA = 32;

	output reg [BITS_DATA-1:0] resultado;
  reg [63:0] resultado64;
	output reg C;
	output reg S;
	output reg O;
	output reg Z;

	input [BITS_DATA-1:0] operando_a;
	input [BITS_DATA-1:0] operando_b;
	input [4:0] opcode;
	
	wire [15:0] bus_address;
  
	  // Con el @*, estamos definiendo un bloque combinacional
	  // ya que no depende de ningún reloj
	  // La lógica combinacional debe usar asignación bloqueante
	always @* begin
	
		//solo hay que hacer la parte de decodificacion de la instruccion, no hay que ejecutarla <- hay que verificar eso
		case (opcode)
			`OP_NOP: begin	//NO OPERATION
				resultado = 'hXXXX_XXXX;
				C = 'bx;
				S = 'bx;
				O = 'bx;
				Z = 'bx;
			end
			
			`OP_HLT: begin	//HALT
				resultado = 'hXXXX_XXXX;
				C = 'bx;
				S = 'bx;
				O = 'bx;
				Z = 'bx;
			end
			
			//`OP_LD: begin 	//LOAD
			
			//end
			
			//`OP_STR: begin	//STORE
			
			//end
			
			`OP_NOT: begin	//NOT gate
				resultado = ~operando_a;
				C = 0;
				S = resultado[BITS_DATA-1];
				O = 0;
				Z = ~(|resultado);
			end
			
			`OP_AND: begin	//AND gate
				resultado = operando_a & operando_b;
				C = 0;
				S = resultado[BITS_DATA-1];
				O = 0;
				Z = ~(|resultado);
			
			end
			
			`OP_OR: begin	//OR gate
				resultado = operando_a | operando_b;
				C = 0;
				S = resultado[BITS_DATA-1];
				O =	0;
				Z = ~(|resultado);
			
			end
			
			//`OP_XOR: begin	//XOR gate
			
			//end
			
			`OP_NEG: begin	//negation
				resultado = -operando_a;			
				C = 0;
				S = resultado[BITS_DATA-1];
				O = 0;
				Z = ~(|resultado);
			end

			`OP_ADD: begin	//addition
				{C,resultado} = operando_a + operando_b;
				S = resultado[BITS_DATA-1];
				// overflow = 1 si el resutlado no tiene el mismo bit de signo que los operandos base
				O = (operando_a[BITS_DATA-1] == operando_b[BITS_DATA-1]) && (operando_a[BITS_DATA-1] !=  resultado[BITS_DATA-1]);
				Z = ~(|resultado);
			end
			
			`OP_SUB: begin	//substraction
				{C,resultado} = operando_a - operando_b;
				S = resultado[BITS_DATA-1];
				O = (operando_a[BITS_DATA-1] == operando_b[BITS_DATA-1]) && (operando_a[BITS_DATA-1] !=  resultado[BITS_DATA-1]);
				Z = ~(|resultado);
			end
			
			`OP_MUL: begin	//multiplication
        resultado64 = operando_a * operando_b;
        resultado = resultado64[31:0];
				S = resultado[BITS_DATA-1:0];
        O = |resultado64[63:32];
				Z = ~(|resultado);
			end
			
			
			
			//`OP_DIV: begin	//division
			
			//end
			
			//`OP_MOD: begin 	//modulo
			
			//end
			
			//`OP_JMP: begin
			
			//end
			
			//`OP_JC: begin
			
			//end
			
			//`OP_JS: begin
			
			//end
			
			//`OP_JO: begin
			
			//end
			
			//`OP_JZ: begin
			
			//end

			default: begin
				// El opcode no esta implementado o bien no es un opcode de ALU valido. Intencionalmente propagaremos Xs (indeterminado) a las salidas 
				resultado = 'hXXXX_XXXX;
				C = 'bx;
				S = 'bx;
				O = 'bx;
				Z = 'bx;
			end
		endcase
	end

endmodule

cpu.v
/*******************************
Universidad de Costa Rica
CI-0114: Fundamentos de Arquitectura

Modulo de CPU completado
Archibald Emmanuel Carrion Claeys
C01736

Ancho de palabra (Datos) 32 bits, ancho de direcciones 16 bits (64Ki Words)
iverilog alu.v cpu.v memoria.v registros.v cpu_tb.v
*********************************/

`include "opcodes.vh"
`define STAGE_FE_0 0	// fetch 0
`define STAGE_FE_1 1	// fetch 1
`define STAGE_DE_0 2	// decode 0
`define STAGE_DE_1 3	// decode 1
`define STAGE_EX_0 4	// execute 0
`define STAGE_EX_1 5	// execute 1
`define STAGE_MA_0 6	// memory access 0
`define STAGE_MA_1 7	// memory access 1
`define STAGE_WB_0 8	// write back 0
`define STAGE_WB_1 9	// write back 1
`define STAGE_HLT  10	// halt



module CPU(MBR_W, write, MAR, MBR_R, reset, clk);
	
	parameter BITS_DATA = 32;
	parameter BITS_ADDR = 16;

	output reg [BITS_DATA-1:0] MBR_W;
	output reg [BITS_ADDR-1:0] MAR;
	output reg                 write;
  
	input  [BITS_DATA-1:0] MBR_R;
	input                  reset;
	input                  clk;
 
	reg [BITS_DATA-1:0] IR;		//	--> instruction actual
	reg [BITS_ADDR-1:0] PC;		//  --> adress of actual instruction
	
	//registros y wires para el ALU
	reg [7:0]           opcode;
	reg [BITS_DATA-1:0] operandoA;
	reg [BITS_DATA-1:0] operandoB;
	reg [2:0] dst;
	reg [2:0] src;
  wire[BITS_DATA-1:0] resultado;
  reg [BITS_DATA-1:0] resultadoReg;
	output wire C, S, O, Z;
	
  //registros y wires para memoria
  wire [BITS_DATA-1:0] salidaMemoria;
  reg [BITS_DATA-1:0] salidaMemoriaReg;
  reg [BITS_DATA-1:0] entradaMemoria;
  reg [BITS_ADDR-1:0] addressMemoria;
  reg writeMemoria;

	//registros y wires para el array de registros
  wire [BITS_DATA-1:0] salidaRegistros;
  reg [BITS_DATA-1:0] salidaRegistrosReg01;
  reg [BITS_DATA-1:0] salidaRegistrosReg02;
  reg [BITS_DATA-1:0] entradaRegistros;
  reg [2:0] addressRegistrosLectura;
  reg [2:0] addressRegistrosEscritura;
  reg writeRegistros;
 
  // registros y wires para el JUMP
  reg [12:0] saltoIntruccion;

	reg [3:0] stage;
  reg [4:0] opcodeReduced;
	
	//se ejecuta la maquina de estado durante los posedge del reloj
	always @(posedge clk or reset) begin
		if (reset) begin
			stage <= `STAGE_FE_0;
			PC    <= 0;  // Podría definirse cualquier otra dirección como primer fetch
		end 
    else begin
			case (stage)

        //############################################################################################

				`STAGE_FE_0: begin
					stage <= `STAGE_FE_1;
					MAR   <= PC;
				end

        //############################################################################################

				`STAGE_FE_1: begin
					stage <= `STAGE_DE_0;
					PC <= PC + 1;				//se incrementa PC para hacer fetch de la instruction siguiente en el proximo ciclo
					IR <= MBR_R;
				end

        //############################################################################################

				`STAGE_DE_0: begin
					stage <= `STAGE_DE_1;
          opcode <= IR[31:24];
          opcodeReduced <= IR[31:27];

          // Decode para la Alu
					operandoA <= IR[23:16];
					operandoB <= IR[15:0];

          // Decode de uso general
          dst <= IR[18:16];
          src <= IR[2:0];

          // Decode para load INM
          entradaRegistros <= IR[15:0];
          // Decode para Load Reg
          addressRegistrosLectura <= IR[2:0];
          // Load directo
          //addressMemoria <= IR[15:0];
          //MAR <= IR[15:0];
          addressRegistrosEscritura <= IR[18:16];

          // Decode para JUMP
          saltoIntruccion = IR[15:3];

					//DECODE 0
				end

        //############################################################################################

				`STAGE_DE_1: begin
					stage <= `STAGE_EX_0;
          // Si desea realizar un load de registro a registro
          // o es un store o un salto
          if (opcodeReduced == 10 || opcodeReduced == 2 || opcode == 209)	begin
            // Lea el valor en ese registro
            writeRegistros = 0;
          end			
					//DECODE 1
				end

        //############################################################################################
				
				`STAGE_EX_0: begin
          // Si es una operacion de la ALU
					if(opcodeReduced>=16 && opcodeReduced<=25) begin
            // Guarde el resultado en un buffer
            resultadoReg <= resultado;
            // Vaya directo a Write-Back (WB)
            stage <= `STAGE_WB_0;
					end 
          else begin
            // Si la instruccion es un salto
            if (opcode == 209) begin
              // guarde el primer valor para comparar
              salidaRegistrosReg01 <= salidaRegistros;

              // Lea el otro valor
              addressRegistrosLectura <= dst;
              writeRegistros <= 0;
            end
            stage <= `STAGE_EX_1;
          end
				end

        //############################################################################################

				`STAGE_EX_1: begin
          // Si es un Load Directo o un store (usa memoria)
          if(opcodeReduced==2 || opcodeReduced==11) begin
            // Vaya a memory access (MA)
            stage <= `STAGE_MA_0;
					end 
          
          else begin
            // Si la instruccion es un salto
            if (opcode == 209) begin
              // guarde el segundo valor para comparar
              salidaRegistrosReg02 <= salidaRegistros;
              
              // Si la condicion de salto se cumple
              if (salidaRegistrosReg01 != salidaRegistrosReg02) begin
                // Cambie la instruccion siguiente a la indicada
                PC <= saltoIntruccion;
                //MAR <= saltoIntruccion;
              end
              // Vuelva al fetch
              stage <= `STAGE_FE_0;
            end

            // Si la instruccion es un Load INM o un Load Reg
            else begin
              stage <= `STAGE_WB_0;
            end
          end
        end

        //############################################################################################

				`STAGE_MA_0: begin	
				  stage <= `STAGE_MA_1;
          // Si estamos haciendo un store
          if (opcodeReduced == 2) begin
            // Guardamos el valor de registros que queremos
            // escribir en memoria
            salidaRegistrosReg01 <= salidaRegistros;
            // Habilitamos escritura
            //writeMemoria = 1;
            write <= 1;
          end
          // Si estamos haciendo un Load directo
          else begin
            // Deshabilitamos escritura
            //writeMemoria = 0;
            write <= 0; //    <== se usa los reg y wires que entran y salen del cpu en vez de tener la meoria adentro del cpu
          end
				end

        //############################################################################################

				`STAGE_MA_1: begin	
          // Si estamos haciendo un store
          if (opcodeReduced == 2) begin
            // Cambiamos el valor de escritura
            //entradaMemoria = salidaRegistrosReg01;
            MBR_W <= salidaRegistrosReg01;    //se guarda en data_in de memoria el valor del registro 
            // Ya has terminado tu funcion
            stage <= `STAGE_FE_0;
          end
          // Si estamos haciendo un Load directo
          else begin
            // Guardamos el valor de la memoria
            //salidaMemoriaReg = salidaMemoria;
            //salidaMemoriaReg <= MBR_R;
            // Continuar con escritura en registros
            stage <= `STAGE_WB_0;
          end
				end

        //############################################################################################

				`STAGE_WB_0: begin
          stage <= `STAGE_WB_1;
          case (opcode)
            `OPD_LD_INM: begin
              // se guarda en un registro el contenido de una celda de memoria de la cual 
              // tenemos el address
              entradaRegistros <= operandoB;
            end
            `OPD_LD_REG: begin
              salidaRegistrosReg01 <= salidaRegistros;  // Guardamos el valor del registro src
              entradaRegistros <= salidaRegistrosReg01; // Cambiamos el valor de escritura al valor de src
            end
            `OPD_LD_DIRECT: begin
              // Cambiamos el valor de escritura al valor de la memoria
              //entradaRegistros <= salidaMemoriaReg;
              //entradaRegistros <= MBR_R;
              //entradaRegistros <= operandoB;
            end
            // Casos de opcode para Alu
            default: begin
              // Cambiamos el valor de escritura al valor obtenido de la Alu
              entradaRegistros <= resultadoReg;
            end
          endcase;
				end

        //############################################################################################

				`STAGE_WB_1: begin
          stage <= `STAGE_FE_0;
          writeRegistros <= 1;    // Escribimos el valor en los registros
				end

        //############################################################################################

				default: begin
					stage <= `STAGE_HLT;
				end

        //############################################################################################

			endcase
		end
	end

ALU alu(resultado, C, S, O, Z, operandoA, operandoB, opcodeReduced);

registersArray registros(.inputData(entradaRegistros), 
											 .dirrInput(addressRegistrosEscritura), 
											 .dirrOutput1(addressRegistrosLectura), 
											 .dirrOutput2(addressRegistrosLectura), 
											 .outputData1(salidaRegistros), 
											 .outputData2(salidaRegistros), 
											 .write_en(writeRegistros), 
											 .clk(clk));

endmodule

cpu_tb.v
/*******************************
Universidad de Costa Rica
CI-0114: Fundamentos de Arquitectura

Prueba y conexion para el CPU y la Memoria
*********************************/

`timescale 1us/100ns

module Memoria_tb;
  wire [31:0] bus_de_datos_salida;
  wire [31:0] bus_de_datos_entrada;
  wire [15:0] bus_de_direcciones;
  wire        bit_de_control_escritura;
  reg         clk;
  reg         reset;
  
  always begin
    #0.5 clk = ~clk;
  end
 
  initial begin
    $dumpfile("cpu.vcd");
    $dumpvars;
    clk = 0; reset = 1;
    #1 reset = 0;
    #128 $finish;
  end
  
  CPU cpu(.MBR_W(bus_de_datos_salida),
          .write(bit_de_control_escritura),
          .MAR(bus_de_direcciones),
          .MBR_R(bus_de_datos_entrada),
          .reset(reset),
          .clk(clk));
  
  Mem_D32b_A16b mem(.data_out(bus_de_datos_entrada), // Note, la salida de la memoria a la entra del CPU
                    .data_in(bus_de_datos_salida),   // Note, la salida del CPU, a la entrada de la memoria
                    .address(bus_de_direcciones),
                    .write(bit_de_control_escritura),
                    .clk(clk));

  
endmodule

cpu.vcd
$date
	Thu Jul 14 12:22:15 2022
$end
$version
	Icarus Verilog
$end
$timescale
	100ns
$end
$scope module Memoria_tb $end
$var wire 16 ! bus_de_direcciones [15:0] $end
$var wire 32 " bus_de_datos_salida [31:0] $end
$var wire 32 # bus_de_datos_entrada [31:0] $end
$var wire 1 $ bit_de_control_escritura $end
$var reg 1 % clk $end
$var reg 1 & reset $end
$scope module cpu $end
$var wire 1 % clk $end
$var wire 1 & reset $end
$var wire 32 ' salidaMemoria [31:0] $end
$var wire 32 ( salidaRegistros [31:0] $end
$var wire 32 ) resultado [31:0] $end
$var wire 1 * Z $end
$var wire 1 + S $end
$var wire 1 , O $end
$var wire 32 - MBR_R [31:0] $end
$var wire 1 . C $end
$var reg 32 / IR [31:0] $end
$var reg 16 0 MAR [15:0] $end
$var reg 32 1 MBR_W [31:0] $end
$var reg 16 2 PC [15:0] $end
$var reg 16 3 addressMemoria [15:0] $end
$var reg 3 4 addressRegistrosEscritura [2:0] $end
$var reg 3 5 addressRegistrosLectura [2:0] $end
$var reg 3 6 dst [2:0] $end
$var reg 32 7 entradaMemoria [31:0] $end
$var reg 32 8 entradaRegistros [31:0] $end
$var reg 8 9 opcode [7:0] $end
$var reg 5 : opcodeReduced [4:0] $end
$var reg 32 ; operandoA [31:0] $end
$var reg 32 < operandoB [31:0] $end
$var reg 32 = resultadoReg [31:0] $end
$var reg 32 > salidaMemoriaReg [31:0] $end
$var reg 32 ? salidaRegistrosReg01 [31:0] $end
$var reg 32 @ salidaRegistrosReg02 [31:0] $end
$var reg 13 A saltoIntruccion [12:0] $end
$var reg 3 B src [2:0] $end
$var reg 4 C stage [3:0] $end
$var reg 1 $ write $end
$var reg 1 D writeMemoria $end
$var reg 1 E writeRegistros $end
$scope module alu $end
$var wire 5 F opcode [4:0] $end
$var wire 32 G operando_a [31:0] $end
$var wire 32 H operando_b [31:0] $end
$var reg 1 . C $end
$var reg 1 , O $end
$var reg 1 + S $end
$var reg 1 * Z $end
$var reg 32 I resultado [31:0] $end
$var reg 64 J resultado64 [63:0] $end
$upscope $end
$scope module registros $end
$var wire 1 % clk $end
$var wire 3 K dirrInput [2:0] $end
$var wire 3 L dirrOutput1 [2:0] $end
$var wire 3 M dirrOutput2 [2:0] $end
$var wire 32 N inputData [31:0] $end
$var wire 1 E write_en $end
$var reg 32 O outputData1 [31:0] $end
$var reg 32 P outputData2 [31:0] $end
$upscope $end
$upscope $end
$scope module mem $end
$var wire 16 Q address [15:0] $end
$var wire 1 % clk $end
$var wire 32 R data_in [31:0] $end
$var wire 32 S data_out [31:0] $end
$var wire 1 $ write $end
$scope begin register[0] $end
$var wire 32 T tmp [31:0] $end
$upscope $end
$scope begin register[1] $end
$var wire 32 U tmp [31:0] $end
$upscope $end
$scope begin register[2] $end
$var wire 32 V tmp [31:0] $end
$upscope $end
$scope begin register[3] $end
$var wire 32 W tmp [31:0] $end
$upscope $end
$scope begin register[4] $end
$var wire 32 X tmp [31:0] $end
$upscope $end
$scope begin register[5] $end
$var wire 32 Y tmp [31:0] $end
$upscope $end
$scope begin register[6] $end
$var wire 32 Z tmp [31:0] $end
$upscope $end
$scope begin register[7] $end
$var wire 32 [ tmp [31:0] $end
$upscope $end
$scope begin register[8] $end
$var wire 32 \ tmp [31:0] $end
$upscope $end
$scope begin register[9] $end
$var wire 32 ] tmp [31:0] $end
$upscope $end
$scope begin register[10] $end
$var wire 32 ^ tmp [31:0] $end
$upscope $end
$scope begin register[11] $end
$var wire 32 _ tmp [31:0] $end
$upscope $end
$scope begin register[12] $end
$var wire 32 ` tmp [31:0] $end
$upscope $end
$scope begin register[13] $end
$var wire 32 a tmp [31:0] $end
$upscope $end
$scope begin register[14] $end
$var wire 32 b tmp [31:0] $end
$upscope $end
$scope begin register[15] $end
$var wire 32 c tmp [31:0] $end
$upscope $end
$scope begin register[16] $end
$var wire 32 d tmp [31:0] $end
$upscope $end
$scope begin register[17] $end
$var wire 32 e tmp [31:0] $end
$upscope $end
$scope begin register[18] $end
$var wire 32 f tmp [31:0] $end
$upscope $end
$scope begin register[19] $end
$var wire 32 g tmp [31:0] $end
$upscope $end
$scope begin register[20] $end
$var wire 32 h tmp [31:0] $end
$upscope $end
$scope begin register[21] $end
$var wire 32 i tmp [31:0] $end
$upscope $end
$scope begin register[22] $end
$var wire 32 j tmp [31:0] $end
$upscope $end
$scope begin register[23] $end
$var wire 32 k tmp [31:0] $end
$upscope $end
$scope begin register[24] $end
$var wire 32 l tmp [31:0] $end
$upscope $end
$scope begin register[25] $end
$var wire 32 m tmp [31:0] $end
$upscope $end
$scope begin register[26] $end
$var wire 32 n tmp [31:0] $end
$upscope $end
$scope begin register[27] $end
$var wire 32 o tmp [31:0] $end
$upscope $end
$scope begin register[28] $end
$var wire 32 p tmp [31:0] $end
$upscope $end
$scope begin register[29] $end
$var wire 32 q tmp [31:0] $end
$upscope $end
$scope begin register[30] $end
$var wire 32 r tmp [31:0] $end
$upscope $end
$scope begin register[31] $end
$var wire 32 s tmp [31:0] $end
$upscope $end
$scope begin register[32] $end
$var wire 32 t tmp [31:0] $end
$upscope $end
$scope begin register[33] $end
$var wire 32 u tmp [31:0] $end
$upscope $end
$scope begin register[34] $end
$var wire 32 v tmp [31:0] $end
$upscope $end
$scope begin register[35] $end
$var wire 32 w tmp [31:0] $end
$upscope $end
$scope begin register[36] $end
$var wire 32 x tmp [31:0] $end
$upscope $end
$scope begin register[37] $end
$var wire 32 y tmp [31:0] $end
$upscope $end
$scope begin register[38] $end
$var wire 32 z tmp [31:0] $end
$upscope $end
$scope begin register[39] $end
$var wire 32 { tmp [31:0] $end
$upscope $end
$scope begin register[40] $end
$var wire 32 | tmp [31:0] $end
$upscope $end
$scope begin register[41] $end
$var wire 32 } tmp [31:0] $end
$upscope $end
$scope begin register[42] $end
$var wire 32 ~ tmp [31:0] $end
$upscope $end
$scope begin register[43] $end
$var wire 32 !" tmp [31:0] $end
$upscope $end
$scope begin register[44] $end
$var wire 32 "" tmp [31:0] $end
$upscope $end
$scope begin register[45] $end
$var wire 32 #" tmp [31:0] $end
$upscope $end
$scope begin register[46] $end
$var wire 32 $" tmp [31:0] $end
$upscope $end
$scope begin register[47] $end
$var wire 32 %" tmp [31:0] $end
$upscope $end
$scope begin register[48] $end
$var wire 32 &" tmp [31:0] $end
$upscope $end
$scope begin register[49] $end
$var wire 32 '" tmp [31:0] $end
$upscope $end
$scope begin register[50] $end
$var wire 32 (" tmp [31:0] $end
$upscope $end
$scope begin register[51] $end
$var wire 32 )" tmp [31:0] $end
$upscope $end
$scope begin register[52] $end
$var wire 32 *" tmp [31:0] $end
$upscope $end
$scope begin register[53] $end
$var wire 32 +" tmp [31:0] $end
$upscope $end
$scope begin register[54] $end
$var wire 32 ," tmp [31:0] $end
$upscope $end
$scope begin register[55] $end
$var wire 32 -" tmp [31:0] $end
$upscope $end
$scope begin register[56] $end
$var wire 32 ." tmp [31:0] $end
$upscope $end
$scope begin register[57] $end
$var wire 32 /" tmp [31:0] $end
$upscope $end
$scope begin register[58] $end
$var wire 32 0" tmp [31:0] $end
$upscope $end
$scope begin register[59] $end
$var wire 32 1" tmp [31:0] $end
$upscope $end
$scope begin register[60] $end
$var wire 32 2" tmp [31:0] $end
$upscope $end
$scope begin register[61] $end
$var wire 32 3" tmp [31:0] $end
$upscope $end
$scope begin register[62] $end
$var wire 32 4" tmp [31:0] $end
$upscope $end
$scope begin register[63] $end
$var wire 32 5" tmp [31:0] $end
$upscope $end
$upscope $end
$upscope $end
$enddefinitions $end
#0
$dumpvars
bx 5"
bx 4"
bx 3"
bx 2"
bx 1"
bx 0"
bx /"
bx ."
bx -"
bx ,"
bx +"
bx *"
bx )"
bx ("
bx '"
bx &"
bx %"
bx $"
bx #"
bx ""
bx !"
bx ~
bx }
bx |
bx {
bx z
bx y
bx x
bx w
bx v
bx u
bx t
bx s
bx r
bx q
bx p
bx o
bx n
bx m
bx l
bx k
bx j
bx i
bx h
bx g
bx f
bx e
bx d
bx c
bx b
bx a
bx `
bx _
bx ^
bx ]
b0 \
b10000000000010001111101000000 [
b11010000000000001111101000000001 Z
b10101000000000100000000000000011 Y
b10111000000000010000000000000010 X
b1011000000000000000000000001 W
b1010000000000000000000000001 V
b1001000000000000000000000001 U
b1000000000000000000000001100 T
bx S
bx R
bx Q
bx P
bx O
bx N
bx M
bx L
bx K
bx J
bx I
bx H
bx G
bx F
xE
xD
b0 C
bx B
bx A
bx @
bx ?
bx >
bx =
bx <
bx ;
bx :
bx 9
bx 8
bx 7
bx 6
bx 5
bx 4
bx 3
b0 2
bx 1
bx 0
bx /
x.
bx -
x,
x+
x*
bx )
bx (
bz '
1&
0%
x$
bx #
bx "
bx !
$end
#5
1%
#10
b1000000000000000000000001100 #
b1000000000000000000000001100 -
b1000000000000000000000001100 S
b0 !
b0 0
b0 Q
b1 C
0%
0&
#15
b1000000000000000000000001100 /
b1 2
b10 C
1%
#20
0%
#25
b1 :
b1 F
b1000 9
b11 C
b1 A
b0 4
b0 K
b1100 3
b100 5
b100 L
b100 M
b1100 8
b1100 N
b100 B
b0 6
b1100 <
b1100 H
b0 ;
b0 G
1%
#30
0%
#35
b100 C
1%
#40
0%
#45
b101 C
1%
#50
0%
#55
b1000 C
1%
#60
0%
#65
b1001 C
bx 8
bx N
1%
#70
0%
#75
b0 C
1E
1%
#80
0%
#85
b1001000000000000000000000001 #
b1001000000000000000000000001 -
b1001000000000000000000000001 S
b1 !
b1 0
b1 Q
b1 C
1%
#90
0%
#95
b1001000000000000000000000001 /
b10 2
b10 C
1%
#100
0%
#105
b1001 9
b11 C
b0 A
b1 3
b1 5
b1 L
b1 M
b1 8
b1 N
b1 B
b1 <
b1 H
1%
#110
0%
#115
b100 C
1%
#120
0%
#125
b101 C
1%
#130
0%
#135
b1000 C
1%
#140
0%
#145
b1001 C
1%
#150
0%
#155
b0 C
1%
#160
0%
#165
b1010000000000000000000000001 #
b1010000000000000000000000001 -
b1010000000000000000000000001 S
b10 !
b10 0
b10 Q
b1 C
1%
#170
0%
#175
b1010000000000000000000000001 /
b11 2
b10 C
1%
#180
0%
#185
b1010 9
b11 C
1%
#190
0%
#195
b100 C
1%
#200
0%
#205
b101 C
1%
#210
0%
#215
b1000 C
1%
#220
0%
#225
b1001 C
bx 8
bx N
1%
#230
0%
#235
b0 C
1%
#240
0%
#245
b1011000000000000000000000001 #
b1011000000000000000000000001 -
b1011000000000000000000000001 S
b11 !
b11 0
b11 Q
b1 C
1%
#250
0%
#255
b1011000000000000000000000001 /
b100 2
b10 C
1%
