memoria.v
/*******************************
Universidad de Costa Rica
CI-0114: Fundamentos de Arquitectura

Simple memoria lectura asincrónica y escritura sincrónica
basada en Flip Flops
1 Puerto de lectura
1 Puerto de escritura

Ancho de palabra (Datos) 32 bits
Ancho de direcciones 16 bits (64Ki Words)

Contiene las primeras words precargadas
Con algunos valores de prueba

*********************************/

module Mem_D32b_A16b(data_out, data_in, address, write, clk);
  parameter BITS_DATA = 32;
  parameter BITS_ADDR = 16;

  output [BITS_DATA-1:0] data_out;
  input  [BITS_DATA-1:0] data_in;
  input  [BITS_ADDR-1:0] address;
  input                  write;
  input                  clk;
  
  reg [BITS_DATA-1:0] data [(2**BITS_ADDR)-1:0];
  
  assign data_out = data[address];
  
  always @(negedge clk) begin
    if (write) begin
      data[address] <= data_in;
    end
  end
  
  // Para leer/escribir archivos de texto como memorias en verilog (nos permite una inicialización más flexible)
  // https://stackoverflow.com/questions/628603/what-is-the-function-of-readmemh-and-writememh-in-verilog
  // Otro tutorial: https://www.fullchipdesign.com/readmemh.htm
  //
  // De momento, los datos se inicializan manualmente
  initial begin    
    //data[0] = 'h00000000;
	  //data[0] = 'hFFFFFFFF; //el estado HLT funciona correctamente
	  data[0] = 'h0000FFFF;
    //00001001 xxxxx000
    data[1] = 'h01005555;
    data[2] = 'h33331111;
	  data[3] = 'hFFFFFFFF;
    //data[3] = 'h00000000;
    //data[4] = 'h00000000;
    //data[5] = 'hF8000000;
  end
  
  // Workaround para lograr visualizar la memoria en gtkwave
  // Agregamos solo los primeros 64 entries para no hacer la simulación
  // innecesariamente lenta
  generate
    genvar idx;
    for(idx = 0; idx < 64; idx = idx + 1) begin: register
      wire [31:0] tmp;
      assign tmp = data[idx];
    end
  endgenerate

endmodule

opcodes.vh
// Modos de direccionamiento (addressing) (son parte del opcode [7:0], específicamente los bits [2:0])
`define DIRECC_IMP    'b000  // Direccionamiento implícito o no necesario para la operación
`define DIRECC_INM    'b001  // Direccionamiento inmediato
`define DIRECC_REG    'b010  // Direccionamiento de registros
`define DIRECC_DIRECT 'b011  // Direccionamiento directo
`define DIRECC_INDREG 'b100  // Direccionamiento indirecto por registros

// Opcodes

// Opcodes especiales
`define OP_NOP        'b00000  // (0x00) Ningúna Operación (hace nada, No Op)
`define OP_HLT        'b11111  // (0x1F) Halt. Detiene la máquina/CPU
// Memoria
`define OP_LD         'b00001  // (0x01)
`define OP_STR        'b00010  // (0x02)
// Lógicas
`define OP_NOT        'b10000  // (0x10)
`define OP_AND        'b10001  // (0x11)
`define OP_OR         'b10010  // (0x12)
`define OP_XOR        'b10011  // (0x13)
// Aritméticas
`define OP_NEG        'b10100  // (0x14)
`define OP_ADD        'b10101  // (0x15)
`define OP_SUB        'b10110  // (0x16)
`define OP_MUL        'b10111  // (0x17)
`define OP_DIV        'b11000  // (0x18)
`define OP_MOD        'b11001  // (0x19)
// Control
`define OP_JMP        'b11010  // (0x1A)
`define OP_JC         'b11011  // (0x1B)
`define OP_JS         'b11100  // (0x1C)
`define OP_JO         'b11101  // (0x1D)
`define OP_JZ         'b11110  // (0x1E)

// Combinaciones válidas de Opcodes y Direccionamiento

// Opcodes especiales
`define OPD_NOP        'b00000_000  // (0x00) Ningúna Operación (hace nada, No Op)
`define OPD_HLT        'b11111_000  // (0xF8) Halt. Detiene la máquina/CPU
// Memoria
// (Para el load, el destino siempre es un registro. La fuente puede variar dependiendo del modo de direccionamiento)
`define OPD_LD_INM     'b00001_001  // (0x09) Carga un valor inmediato al registro. Ya que el valor inmediato son 16 bits y el registro 32 bits, se hará extensión de signo
`define OPD_LD_REG     'b00001_010  // (0x0A) Load entre registros. Permite mover fácilmente el valor de un Registro A a otro Registro B
`define OPD_LD_DIRECT  'b00001_011  // (0x0B)
`define OPD_LD_INDREG  'b00001_100  // (0x0C)
// (Para el store, la fuente siempre es un registro. El destino puede variar dependiendo del modo de direccionamiento)
`define OPD_STR_DIRECT 'b00010_011  // (0x13)
`define OPD_STR_INDREG 'b00010_100  // (0x14)
// Lógicas (Todas usa direccionamiento de registros únicamente)
`define OPD_NOT        'b10000_010  // (0x82)
`define OPD_AND        'b10001_010  // (0x86)
`define OPD_OR         'b10010_010  // (0x92)
`define OPD_XOR        'b10011_010  // (0x96)
// Aritméticas (Todas usa direccionamiento de registros únicamente)
`define OPD_NEG        'b10100_010  // (0xA2)
`define OPD_ADD        'b10101_010  // (0xA6)
`define OPD_SUB        'b10110_010  // (0xB2)
`define OPD_MUL        'b10111_010  // (0xB6)
`define OPD_DIV        'b11000_010  // (0xC2)
`define OPD_MOD        'b11001_010  // (0xC6)
// Control (Todas son saltos absolutos, y usan direccionamiento inmediato únicamente)
`define OPD_JMP        'b11010_001  // (0xD1)
`define OPD_JC         'b11011_001  // (0xD9)
`define OPD_JS         'b11100_001  // (0xE1)
`define OPD_JO         'b11101_001  // (0xE9)
`define OPD_JZ         'b11110_001  // (0xF1)

// Para ver los opcodes con nombres en GTKWave
// https://electronics.stackexchange.com/questions/530123/viewing-verilog-enums-in-iverilog-gtkwave

// Create a file with the extension gtkw. This file contains how you want the state variable to be displayed on
// the waveform. For your example it would be:
//
// 00 STATE0
// 01 STATE1
// 10 STATE2
//
// Because you have used logic type which is 2 bits wide and have not encoded the state variables, SystemVerilog
// assigns the state variables the default values in ascending order. In this case the default binary values would
// be from 00 to 10 since you have 3 State variables.
// 
// Open the waveform and dump the signal. Do  Right-Mouse -> Data Format -> Translate Filter File -> Enable and Select.
// The Select Signal Filter Dialog Box opens. Then left click on Add Filter to List button. Select the gtkw extension file
// that you created. This file will then be displayed in the Select Signal Filter dialog box. Select your file in the Select
// Filter Dialog Box, make sure it is highlighted, then left click on the OK button. The binary signals in the waveform should
// be replaced with the enum values.

registros.v
/*******************************
Universidad de Costa Rica
CI-0114: Fundamentos de Arquitectura

Circuito simple de registro que permite almacenar 32 bits

iverilog registros.v registros_tb.v
*****************************/

module registersArray(inputData, dirrInput, dirrOutput1, dirrOutput2, outputData1, outputData2, write_en);
	parameter BITS_DATA = 32;								//tamano de los registros
	parameter BITS_ADDR = 3;								//tamano de las dirreciones
	
	input [BITS_DATA-1:0] inputData;						//data que hay que agregar en uno de los registros
	input [BITS_ADDR-1:0] dirrInput;						//posicion donde hay que agregar el data inputData
	input [BITS_ADDR-1:0] dirrOutput1;						//posicion del elemento que se quiere sacar de la lista de registros y se guarda en outputData1
	input [BITS_ADDR-1:0] dirrOutput2;						//posicion del elemento que se quiere sacar de la lista de registros y se guarda en outputData2
	input write_en;											// abreviado para "write enable", si esta en 1 permite cambiar el contenido de los registros, sino no puede
	output reg [BITS_DATA-1:0] outputData1;					//data sacado del array de registros
	output reg [BITS_DATA-1:0] outputData2;					//data sacado del array de registros
	
	//"arreglo" de todos los registers de 32 bits
	reg [BITS_DATA-1:0] R0;
	reg [BITS_DATA-1:0] R1;
	reg [BITS_DATA-1:0] R2;
	reg [BITS_DATA-1:0] R3;
	reg [BITS_DATA-1:0] R4;
	reg [BITS_DATA-1:0] R5;
	reg [BITS_DATA-1:0] R6;
	reg [BITS_DATA-1:0] R7;
	
	//para agregar un elemento en el arreglo de registros
	always @(dirrInput) begin
		if(write_en) begin
			case (dirrInput)
				'b000: begin
					R0 = inputData;
					
				end
				
				'b001: begin
					R1 = inputData;
				end
				
				'b010: begin
					R2 = inputData;
				end
				
				'b011: begin
					R3 = inputData;
				end
				
				'b100: begin
					R4 = inputData;
				end
				
				'b101: begin
					R5 = inputData;
				end
				
				'b110: begin
					R6 = inputData;
				end
				
				'b111: begin
					R7 = inputData;
				end
				
				default: begin
					//default case
				end
			endcase	
		end
	end
	
	//para sacar un primer elemento del arreglo de registros
	always @(dirrOutput1) begin
		case (dirrOutput1)
			'b000: begin
				outputData1 = R0;
				//dirrOutput1 <= R0[7:5];
			end
			
			'b001: begin
				outputData1 = R1;
				//dirrOutput1 <= R1[7:5];
			end
			
			'b010: begin
				outputData1 = R2;
				//dirrOutput1 <= R2[7:5];
			end
			
			'b011: begin
				outputData1 = R3;
				//dirrOutput1 <= R3[7:5];
			end
			
			'b100: begin
				outputData1 = R4;
				//dirrOutput1 <= R4[7:5];
			end
			
			'b101: begin
				outputData1 = R5;
				//dirrOutput1 <= R5[7:5];
			end
			
			'b110: begin
				outputData1 = R6;
				//dirrOutput1 <= R6[7:5];
			end
			
			'b111: begin
				outputData1 = R7;
				//dirrOutput1 <= R7[7:5];
			end
			
			default: begin
				//default case
			end
		endcase	
	end
	
	//para sacar un segundo elemento del arreglo de registros
	always @(dirrOutput2) begin
		case (dirrOutput2)
			'b000: begin
				outputData2 = R0;
				//dirrOutput1 <= R0[7:5];
			end
			
			'b001: begin
				outputData2 = R1;
				//dirrOutput1 <= R1[7:5];
			end
			
			'b010: begin
				outputData2 = R2;
				//dirrOutput1 <= R2[7:5];
			end
			
			'b011: begin
				outputData2 = R3;
				//dirrOutput1 <= R3[7:5];
			end
			
			'b100: begin
				outputData2 = R4;
				//dirrOutput1 <= R4[7:5];
			end
			
			'b101: begin
				outputData2 = R5;
				//dirrOutput1 <= R5[7:5];
			end
			
			'b110: begin
				outputData2 = R6;
				//dirrOutput1 <= R6[7:5];
			end
			
			'b111: begin
				outputData2 = R7;
				//dirrOutput1 <= R7[7:5];
			end
			
			default: begin
				//default case
			end
		endcase	
	end
	
	//para sacar un segundo elemento del arreglo de registros
	/*always @(dirrOutput2) begin
		case (dirrInput)
			'b000: begin
				//code
			end
			
			'b001: begin
				//code
			end
			
			'b010: begin
				//code
			end
			
			'b011: begin
				//code
			end
			
			'b100: begin
				//code
			end
			
			'b101: begin
				//code
			end
			
			'b110: begin
				//code
			end
			
			'b111: begin
				//code
			end
			
			default: begin
				//code
			end
		endcase	
	end*/
	//WE WILL USE A SWITCH FOR EVERY CASE OF DIRR OUTPUT
	
	
	//parameter BITS_DATA = 32;
	//parameter BITS_ADDR = 16;
	
	//output [BITS_DATA-1:0] dataOutput;
	//wire dataOutput;
	//output [BITS_ADDR-1:0] dirrOutput;
	//wire dirrOutput;
	//input [BITS_DATA-1:0] dataInput;
	//wire dataInput;
//	reg dataInput, dataOutput, dirrOutput;
	
	//reg [BITS_DATA-1:0] contentRegister;
	
	//always @ (dataInput) begin
		//contentRegister = dataInput;
		//dirrOutput = contentRegister[16:BITS_DATA-1];
		//dataOutput = dataInput;
//	end
	
endmodule

alu.v
/*******************************
Universidad de Costa Rica
CI-0114: Fundamentos de Arquitectura

Modulo de una ALU combinacional,
parcialmente implementada

*********************************/

`include "opcodes.vh"

module ALU(resultado, C, S, O, Z, operando_a, operando_b, opcode);
  parameter BITS_DATA = 32;

  output reg [BITS_DATA-1:0] resultado;
  output reg C;
  output reg S;
  output reg O;
  output reg Z;

  input [BITS_DATA-1:0] operando_a;
  input [BITS_DATA-1:0] operando_b;
  input [4:0] opcode;
  
  // Con el @*, estamos definiendo un bloque combinacional
  // ya que no depende de ningún reloj
  // La lógica combinacional debe usar asignación bloqueante
  always @* begin
    case (opcode)
      `OP_NOT: begin
        resultado = ~operando_a;
        C = 0;
        S = resultado[BITS_DATA-1];
        O = 0;
        Z = ~(|resultado);
      end

      `OP_ADD: begin
        {C,resultado} = operando_a + operando_b;
        S = resultado[BITS_DATA-1];
        // Overflow es 1 cuando hay cambio en el bit de signo. Solo
        // puedo ocurrir cuando los operandos tienen el mismo signo
        O = (operando_a[BITS_DATA-1] == operando_b[BITS_DATA-1]) &&
            (operando_a[BITS_DATA-1] !=  resultado[BITS_DATA-1]);
        Z = ~(|resultado);
      end

      default: begin
        // El opcode no esta implementado o bien no es un
        // opcode de ALU valido. Intencionalmente propagaremos
        // Xs (indeterminado) a las salidas 
        resultado = 'hXXXX_XXXX;
        C = 'bx;
        S = 'bx;
        O = 'bx;
        Z = 'bx;
      end
    endcase
  end

endmodule

cpu.v
/*******************************
Universidad de Costa Rica
CI-0114: Fundamentos de Arquitectura

Modulo de CPU completado
Archibald Emmanuel Carrion Claeys
C01736

Ancho de palabra (Datos) 32 bits, ancho de direcciones 16 bits (64Ki Words)
iverilog alu.v cpu.v memoria.v registros.v cpu_tb.v
*********************************/

`include "opcodes.vh"

`define STAGE_FE_0 0	// fetch 0
`define STAGE_FE_1 1	// fetch 1
`define STAGE_DE_0 2	// decode 0
`define STAGE_DE_1 3	// decode 1
`define STAGE_EX_0 4	// execute 0
`define STAGE_EX_1 5	// execute 1
`define STAGE_MA_0 6	// memory access 0
`define STAGE_MA_1 7	// memory access 1
`define STAGE_WB_0 8	// write back 0
`define STAGE_WB_1 9	// write back 1
`define STAGE_HLT  10	// halt

module CPU(MBR_W, write, MAR, MBR_R, reset, clk);
	
	parameter BITS_DATA = 32;
	parameter BITS_ADDR = 16;

	output reg [BITS_DATA-1:0] MBR_W;
	output reg [BITS_ADDR-1:0] MAR;
	output reg                 write;
  
	input  [BITS_DATA-1:0] MBR_R;
	input                  reset;
	input                  clk;
 
	reg [BITS_DATA-1:0] IR;		//	--> instruction actual
	reg [BITS_ADDR-1:0] PC;		//  --> adress of actual instruction
	
	//registros y wires para el ALU
	reg [4:0]           opcode;
	reg [2:0]           dirReg;
	reg [BITS_DATA-1:0] operandoA;
	reg [BITS_DATA-1:0] operandoB;
	wire [31:0] R;
	wire C, S, O, Z;
	
	//registros y wires para el array de registros
	reg [31:0] _inputData;
	reg [2:0] _dirrInput;
	reg [2:0] _dirrOutput1;
	reg [2:0] _dirrOutput2;
	reg _enableWrite;
	wire [31:0] _outputData1;
	wire [31:0] _outputData2;
 
	reg [3:0] stage;
	
	//se ejecuta la maquina de estado durante los posedge del reloj
	always @(posedge clk or reset) begin
		if (reset) begin
			stage <= `STAGE_FE_0;
			PC    <= 0;  // Podría definirse cualquier otra dirección como primer fetch
		end else begin
			case (stage)
				`STAGE_FE_0: begin
					stage <= `STAGE_FE_1;
					MAR   <= PC;
				end

				`STAGE_FE_1: begin
					stage <= `STAGE_DE_0;
					PC <= PC + 1;
					IR <= MBR_R;
				end

				`STAGE_DE_0: begin
					stage <= `STAGE_DE_1;
					opcode <= IR[31:27];
					opcode = IR[31:24];
					dirReg = IR[26:24];
					//DECODE 0
				end

				`STAGE_DE_1: begin
					stage <= `STAGE_EX_0;
					
					operandoA = IR[23:16];
					operandoB = IR[15:0];
					//DECODE 1
				end
				
				`STAGE_EX_0: begin
				  stage <= `STAGE_EX_1;
				  //hay que "llamar" el alu con los operandos y el opcode dado
				end

				`STAGE_EX_1: begin
				  stage <= `STAGE_MA_0;
				end

				`STAGE_MA_0: begin
				  stage <= `STAGE_MA_1;
				end

				`STAGE_MA_1: begin
				  stage <= `STAGE_WB_0;
				end

				`STAGE_WB_0: begin
					stage <= `STAGE_WB_1;
				end

				`STAGE_WB_1: begin
					stage <= `STAGE_FE_0;
				end

				default: begin
					stage <= `STAGE_HLT;
				end
			endcase
		end
	end
	
	//se guarda los valores en los registros cuando es el negedge del reloj
	always @(negedge clk) begin
		//code
	end
	
	ALU alu(.resultado(R), .C(C), .S(S), .O(O), .Z(Z), .operando_a(operandoA), .operando_b(operandoB), .opcode(opcode));
	registersArray registro(IR, _dirrInput, _dirrOutput1, _dirrOutput2, _outputData1, _outputData2, _enableWrite);
	//ALU alu(resultado, C, S, O, Z, operando_a, operando_b, opcode);
endmodule

cpu_tb.v
/*******************************
Universidad de Costa Rica
CI-0114: Fundamentos de Arquitectura

Prueba y conexion para el CPU y la Memoria
*********************************/

`timescale 1us/100ns

module Memoria_tb;
  wire [31:0] bus_de_datos_salida;
  wire [31:0] bus_de_datos_entrada;
  wire [15:0] bus_de_direcciones;
  wire        bit_de_control_escritura;
  reg         clk;
  reg         reset;
  
  always begin
    #0.5 clk = ~clk;
  end
 
  initial begin
    $dumpfile("CPU_y_Memoria.vcd");
    $dumpvars;
    clk = 0; reset = 1;
    #1 reset = 0;
    #128 $finish;
  end
  
  CPU cpu(.MBR_W(bus_de_datos_salida),
          .write(bit_de_control_escritura),
          .MAR(bus_de_direcciones),
          .MBR_R(bus_de_datos_entrada),
          .reset(reset),
          .clk(clk));
  
  Mem_D32b_A16b mem(.data_out(bus_de_datos_entrada), // Note, la salida de la memoria a la entra del CPU
                    .data_in(bus_de_datos_salida),   // Note, la salida del CPU, a la entrada de la memoria
                    .address(bus_de_direcciones),
                    .write(bit_de_control_escritura),
                    .clk(clk));
endmodule

CPU_y_Memoria.vcd
$date
	Thu Jun 16 21:36:05 2022
$end
$version
	Icarus Verilog
$end
$timescale
	100ns
$end
$scope module Memoria_tb $end
$var wire 16 ! bus_de_direcciones [15:0] $end
$var wire 32 " bus_de_datos_salida [31:0] $end
$var wire 32 # bus_de_datos_entrada [31:0] $end
$var wire 1 $ bit_de_control_escritura $end
$var reg 1 % clk $end
$var reg 1 & reset $end
$scope module cpu $end
$var wire 1 % clk $end
$var wire 1 & reset $end
$var wire 32 ' _outputData2 [31:0] $end
$var wire 32 ( _outputData1 [31:0] $end
$var wire 1 ) Z $end
$var wire 1 * S $end
$var wire 32 + R [31:0] $end
$var wire 1 , O $end
$var wire 32 - MBR_R [31:0] $end
$var wire 1 . C $end
$var reg 32 / IR [31:0] $end
$var reg 16 0 MAR [15:0] $end
$var reg 32 1 MBR_W [31:0] $end
$var reg 16 2 PC [15:0] $end
$var reg 3 3 _dirrInput [2:0] $end
$var reg 3 4 _dirrOutput1 [2:0] $end
$var reg 3 5 _dirrOutput2 [2:0] $end
$var reg 1 6 _enableWrite $end
$var reg 3 7 dirReg [2:0] $end
$var reg 5 8 opcode [4:0] $end
$var reg 32 9 operandoA [31:0] $end
$var reg 32 : operandoB [31:0] $end
$var reg 4 ; stage [3:0] $end
$var reg 1 $ write $end
$scope module alu $end
$var wire 5 < opcode [4:0] $end
$var wire 32 = operando_a [31:0] $end
$var wire 32 > operando_b [31:0] $end
$var reg 1 . C $end
$var reg 1 , O $end
$var reg 1 * S $end
$var reg 1 ) Z $end
$var reg 32 ? resultado [31:0] $end
$upscope $end
$scope module registro $end
$var wire 3 @ dirrInput [2:0] $end
$var wire 3 A dirrOutput1 [2:0] $end
$var wire 3 B dirrOutput2 [2:0] $end
$var wire 32 C inputData [31:0] $end
$var wire 1 6 write_en $end
$var reg 32 D R0 [31:0] $end
$var reg 32 E R1 [31:0] $end
$var reg 32 F R2 [31:0] $end
$var reg 32 G R3 [31:0] $end
$var reg 32 H R4 [31:0] $end
$var reg 32 I R5 [31:0] $end
$var reg 32 J R6 [31:0] $end
$var reg 32 K R7 [31:0] $end
$var reg 32 L outputData1 [31:0] $end
$var reg 32 M outputData2 [31:0] $end
$upscope $end
$upscope $end
$scope module mem $end
$var wire 16 N address [15:0] $end
$var wire 1 % clk $end
$var wire 32 O data_in [31:0] $end
$var wire 32 P data_out [31:0] $end
$var wire 1 $ write $end
$scope begin register[0] $end
$var wire 32 Q tmp [31:0] $end
$upscope $end
$scope begin register[1] $end
$var wire 32 R tmp [31:0] $end
$upscope $end
$scope begin register[2] $end
$var wire 32 S tmp [31:0] $end
$upscope $end
$scope begin register[3] $end
$var wire 32 T tmp [31:0] $end
$upscope $end
$scope begin register[4] $end
$var wire 32 U tmp [31:0] $end
$upscope $end
$scope begin register[5] $end
$var wire 32 V tmp [31:0] $end
$upscope $end
$scope begin register[6] $end
$var wire 32 W tmp [31:0] $end
$upscope $end
$scope begin register[7] $end
$var wire 32 X tmp [31:0] $end
$upscope $end
$scope begin register[8] $end
$var wire 32 Y tmp [31:0] $end
$upscope $end
$scope begin register[9] $end
$var wire 32 Z tmp [31:0] $end
$upscope $end
$scope begin register[10] $end
$var wire 32 [ tmp [31:0] $end
$upscope $end
$scope begin register[11] $end
$var wire 32 \ tmp [31:0] $end
$upscope $end
$scope begin register[12] $end
$var wire 32 ] tmp [31:0] $end
$upscope $end
$scope begin register[13] $end
$var wire 32 ^ tmp [31:0] $end
$upscope $end
$scope begin register[14] $end
$var wire 32 _ tmp [31:0] $end
$upscope $end
$scope begin register[15] $end
$var wire 32 ` tmp [31:0] $end
$upscope $end
$scope begin register[16] $end
$var wire 32 a tmp [31:0] $end
$upscope $end
$scope begin register[17] $end
$var wire 32 b tmp [31:0] $end
$upscope $end
$scope begin register[18] $end
$var wire 32 c tmp [31:0] $end
$upscope $end
$scope begin register[19] $end
$var wire 32 d tmp [31:0] $end
$upscope $end
$scope begin register[20] $end
$var wire 32 e tmp [31:0] $end
$upscope $end
$scope begin register[21] $end
$var wire 32 f tmp [31:0] $end
$upscope $end
$scope begin register[22] $end
$var wire 32 g tmp [31:0] $end
$upscope $end
$scope begin register[23] $end
$var wire 32 h tmp [31:0] $end
$upscope $end
$scope begin register[24] $end
$var wire 32 i tmp [31:0] $end
$upscope $end
$scope begin register[25] $end
$var wire 32 j tmp [31:0] $end
$upscope $end
$scope begin register[26] $end
$var wire 32 k tmp [31:0] $end
$upscope $end
$scope begin register[27] $end
$var wire 32 l tmp [31:0] $end
$upscope $end
$scope begin register[28] $end
$var wire 32 m tmp [31:0] $end
$upscope $end
$scope begin register[29] $end
$var wire 32 n tmp [31:0] $end
$upscope $end
$scope begin register[30] $end
$var wire 32 o tmp [31:0] $end
$upscope $end
$scope begin register[31] $end
$var wire 32 p tmp [31:0] $end
$upscope $end
$scope begin register[32] $end
$var wire 32 q tmp [31:0] $end
$upscope $end
$scope begin register[33] $end
$var wire 32 r tmp [31:0] $end
$upscope $end
$scope begin register[34] $end
$var wire 32 s tmp [31:0] $end
$upscope $end
$scope begin register[35] $end
$var wire 32 t tmp [31:0] $end
$upscope $end
$scope begin register[36] $end
$var wire 32 u tmp [31:0] $end
$upscope $end
$scope begin register[37] $end
$var wire 32 v tmp [31:0] $end
$upscope $end
$scope begin register[38] $end
$var wire 32 w tmp [31:0] $end
$upscope $end
$scope begin register[39] $end
$var wire 32 x tmp [31:0] $end
$upscope $end
$scope begin register[40] $end
$var wire 32 y tmp [31:0] $end
$upscope $end
$scope begin register[41] $end
$var wire 32 z tmp [31:0] $end
$upscope $end
$scope begin register[42] $end
$var wire 32 { tmp [31:0] $end
$upscope $end
$scope begin register[43] $end
$var wire 32 | tmp [31:0] $end
$upscope $end
$scope begin register[44] $end
$var wire 32 } tmp [31:0] $end
$upscope $end
$scope begin register[45] $end
$var wire 32 ~ tmp [31:0] $end
$upscope $end
$scope begin register[46] $end
$var wire 32 !" tmp [31:0] $end
$upscope $end
$scope begin register[47] $end
$var wire 32 "" tmp [31:0] $end
$upscope $end
$scope begin register[48] $end
$var wire 32 #" tmp [31:0] $end
$upscope $end
$scope begin register[49] $end
$var wire 32 $" tmp [31:0] $end
$upscope $end
$scope begin register[50] $end
$var wire 32 %" tmp [31:0] $end
$upscope $end
$scope begin register[51] $end
$var wire 32 &" tmp [31:0] $end
$upscope $end
$scope begin register[52] $end
$var wire 32 '" tmp [31:0] $end
$upscope $end
$scope begin register[53] $end
$var wire 32 (" tmp [31:0] $end
$upscope $end
$scope begin register[54] $end
$var wire 32 )" tmp [31:0] $end
$upscope $end
$scope begin register[55] $end
$var wire 32 *" tmp [31:0] $end
$upscope $end
$scope begin register[56] $end
$var wire 32 +" tmp [31:0] $end
$upscope $end
$scope begin register[57] $end
$var wire 32 ," tmp [31:0] $end
$upscope $end
$scope begin register[58] $end
$var wire 32 -" tmp [31:0] $end
$upscope $end
$scope begin register[59] $end
$var wire 32 ." tmp [31:0] $end
$upscope $end
$scope begin register[60] $end
$var wire 32 /" tmp [31:0] $end
$upscope $end
$scope begin register[61] $end
$var wire 32 0" tmp [31:0] $end
$upscope $end
$scope begin register[62] $end
$var wire 32 1" tmp [31:0] $end
$upscope $end
$scope begin register[63] $end
$var wire 32 2" tmp [31:0] $end
$upscope $end
$upscope $end
$upscope $end
$enddefinitions $end
#0
$dumpvars
bx 2"
bx 1"
bx 0"
bx /"
bx ."
bx -"
bx ,"
bx +"
bx *"
bx )"
bx ("
bx '"
bx &"
bx %"
bx $"
bx #"
bx ""
bx !"
bx ~
bx }
bx |
bx {
bx z
bx y
bx x
bx w
bx v
bx u
bx t
bx s
bx r
bx q
bx p
bx o
bx n
bx m
bx l
bx k
bx j
bx i
bx h
bx g
bx f
bx e
bx d
bx c
bx b
bx a
bx `
bx _
bx ^
bx ]
bx \
bx [
bx Z
bx Y
bx X
bx W
b11111000000000000000000000000000 V
b0 U
b0 T
b0 S
b0 R
b0 Q
bx P
bx O
bx N
bx M
bx L
bx K
bx J
bx I
bx H
bx G
bx F
bx E
bx D
bx C
bx B
bx A
bx @
bx ?
bx >
bx =
bx <
b0 ;
bx :
bx 9
bx 8
bx 7
x6
bx 5
bx 4
bx 3
b0 2
bx 1
bx 0
bx /
x.
bx -
x,
bx +
x*
x)
bx (
bx '
1&
0%
x$
bx #
bx "
bx !
$end
#5
1%
#10
b0 #
b0 -
b0 P
b0 !
b0 0
b0 N
b1 ;
0%
0&
#15
b0 /
b0 C
b1 2
b10 ;
1%
#20
0%
#25
b11 ;
b0 7
b0 8
b0 <
1%
#30
0%
#35
b100 ;
b0 :
b0 >
b0 9
b0 =
1%
#40
0%
#45
b101 ;
1%
#50
0%
#55
b110 ;
1%
#60
0%
#65
b111 ;
1%
#70
0%
#75
b1000 ;
1%
#80
0%
#85
b1001 ;
1%
#90
0%
#95
b0 ;
1%
#100
0%
#105
b1 !
b1 0
b1 N
b1 ;
1%
#110
0%
#115
b10 2
b10 ;
1%
#120
0%
#125
b11 ;
1%
#130
0%
#135
b100 ;
1%
#140
0%
#145
b101 ;
1%
#150
0%
#155
b110 ;
1%
#160
0%
#165
b111 ;
1%
#170
0%
#175
b1000 ;
1%
#180
0%
#185
b1001 ;
1%
#190
0%
#195
b0 ;
1%
#200
0%
#205
b10 !
b10 0
b10 N
b1 ;
1%
#210
0%
#215
b11 2
b10 ;
1%
#220
0%
#225
b11 ;
1%
#230
0%
#235
b100 ;
1%
#240
0%
#245
b101 ;
1%
#250
0%
#255
b110 ;
1%
#260
0%
#265
b111 ;
1%
#270
0%
#275
b1000 ;
1%
#280
0%
#285
b1001 ;
1%
#290
0%
#295
b0 ;
1%
#300
0%
#305
b11 !
b11 0
b11 N
b1 ;
1%
#310
0%
#315
b100 2
b10 ;
1%
#320
0%
#325
b11 ;
1%
#330
0%
#335
b100 ;
1%
#340
0%
#345
b101 ;
1%
#350
0%
#355
b110 ;
1%
#360
0%
#365
b111 ;
1%
#370
0%
#375
b1000 ;
1%
#380
0%
#385
b1001 ;
1%
#390
0%
#395
b0 ;
1%
#400
0%
#405
b100 !
b100 0
b100 N
b1 ;
1%
#410
0%
#415
b101 2
b10 ;
1%
#420
0%
#425
b11 ;
1%
#430
0%
#435
b100 ;
1%
#440
0%
#445
b101 ;
1%
#450
0%
#455
b110 ;
1%
#460
0%
#465
b111 ;
1%
#470
0%
#475
b1000 ;
1%
#480
0%
#485
b1001 ;
1%
#490
0%
#495
b0 ;
1%
#500
0%
#505
b11111000000000000000000000000000 #
b11111000000000000000000000000000 -
b11111000000000000000000000000000 P
b101 !
b101 0
b101 N
b1 ;
1%
#510
0%
#515
b11111000000000000000000000000000 /
b11111000000000000000000000000000 C
b110 2
b10 ;
1%
#520
0%
#525
b11 ;
b11111 8
b11111 <
1%
#530
0%
#535
b100 ;
1%
#540
0%
#545
b101 ;
1%
#550
0%
#555
b110 ;
1%
#560
0%
#565
b111 ;
1%
#570
0%
#575
b1000 ;
1%
#580
0%
#585
b1001 ;
1%
#590
0%
#595
b0 ;
1%
#600
0%
#605
bx #
bx -
bx P
b110 !
b110 0
b110 N
b1 ;
1%
#610
0%
#615
bx /
bx C
b111 2
b10 ;
1%
#620
0%
#625
b11 ;
bx 7
bx 8
bx <
1%
#630
0%
#635
b100 ;
b0xxxxxxxxxxxxxxxx :
b0xxxxxxxxxxxxxxxx >
b0xxxxxxxx 9
b0xxxxxxxx =
1%
#640
0%
#645
b101 ;
1%
#650
0%
#655
b110 ;
1%
#660
0%
#665
b111 ;
1%
#670
0%
#675
b1000 ;
1%
#680
0%
#685
b1001 ;
1%
#690
0%
#695
b0 ;
1%
#700
0%
#705
b111 !
b111 0
b111 N
b1 ;
1%
#710
0%
#715
b1000 2
b10 ;
1%
#720
0%
#725
b11 ;
1%
#730
0%
#735
b100 ;
1%
#740
0%
#745
b101 ;
1%
#750
0%
#755
b110 ;
1%
#760
0%
#765
b111 ;
1%
#770
0%
#775
b1000 ;
1%
#780
0%
#785
b1001 ;
1%
#790
0%
#795
b0 ;
1%
#800
0%
#805
b1000 !
b1000 0
b1000 N
b1 ;
1%
#810
0%
#815
b1001 2
b10 ;
1%
#820
0%
#825
b11 ;
1%
#830
0%
#835
b100 ;
1%
#840
0%
#845
b101 ;
1%
#850
0%
#855
b110 ;
1%
#860
0%
#865
b111 ;
1%
#870
0%
#875
b1000 ;
1%
#880
0%
#885
b1001 ;
1%
#890
0%
#895
b0 ;
1%
#900
0%
#905
b1001 !
b1001 0
b1001 N
b1 ;
1%
#910
0%
#915
b1010 2
b10 ;
1%
#920
0%
#925
b11 ;
1%
#930
0%
#935
b100 ;
1%
#940
0%
#945
b101 ;
1%
#950
0%
#955
b110 ;
1%
#960
0%
#965
b111 ;
1%
#970
0%
#975
b1000 ;
1%
#980
0%
#985
b1001 ;
1%
#990
0%
#995
b0 ;
1%
#1000
0%
#1005
b1010 !
b1010 0
b1010 N
b1 ;
1%
#1010
0%
#1015
b1011 2
b10 ;
1%
#1020
0%
#1025
b11 ;
1%
#1030
0%
#1035
b100 ;
1%
#1040
0%
#1045
b101 ;
1%
#1050
0%
#1055
b110 ;
1%
#1060
0%
#1065
b111 ;
1%
#1070
0%
#1075
b1000 ;
1%
#1080
0%
#1085
b1001 ;
1%
#1090
0%
#1095
b0 ;
1%
#1100
0%
#1105
b1011 !
b1011 0
b1011 N
b1 ;
1%
#1110
0%
