registros.v
/*******************************
Universidad de Costa Rica
CI-0114: Fundamentos de Arquitectura

Circuito simple de registro que permite almacenar 32 bits

iverilog registros.v registros_tb.v
*****************************/

module registersArray(inputData, dirrInput, dirrOutput1, dirrOutput2, outputData1, outputData2);
	parameter BITS_DATA = 32;								//tamano de los registros
	parameter BITS_ADDR = 3;								//tamano de las dirreciones
	
	input [BITS_DATA-1:0] inputData;						//data que hay que agregar en uno de los registros
	input [BITS_ADDR-1:0] dirrInput;						//posicion donde hay que agregar el data inputData
	input [BITS_ADDR-1:0] dirrOutput1;						//posicion del elemento que se quiere sacar de la lista de registros y se guarda en outputData1
	input [BITS_ADDR-1:0] dirrOutput2;						//posicion del elemento que se quiere sacar de la lista de registros y se guarda en outputData2
	output reg [BITS_DATA-1:0] outputData1;					//data sacado del array de registros
	output reg [BITS_DATA-1:0] outputData2;					//data sacado del array de registros
	
	//"arreglo" de todos los registers de 32 bits
	reg [BITS_DATA-1:0] R0;
	reg [BITS_DATA-1:0] R1;
	reg [BITS_DATA-1:0] R2;
	reg [BITS_DATA-1:0] R3;
	reg [BITS_DATA-1:0] R4;
	reg [BITS_DATA-1:0] R5;
	reg [BITS_DATA-1:0] R6;
	reg [BITS_DATA-1:0] R7;
	
	//para agregar un elemento en el arreglo de registros
	always @(dirrInput) begin
		case (dirrInput)
			'b000: begin
				R0 = inputData;
				
			end
			
			'b001: begin
				R1 = inputData;
			end
			
			'b010: begin
				R2 = inputData;
			end
			
			'b011: begin
				R3 = inputData;
			end
			
			'b100: begin
				R4 = inputData;
			end
			
			'b101: begin
				R5 = inputData;
			end
			
			'b110: begin
				R6 = inputData;
			end
			
			'b111: begin
				R7 = inputData;
			end
			
			default: begin
				//default case
			end
		endcase	
	end
	
	//para sacar un primer elemento del arreglo de registros
	always @(dirrOutput1) begin
		case (dirrOutput1)
			'b000: begin
				outputData1 = R0;
				//dirrOutput1 <= R0[7:5];
			end
			
			'b001: begin
				outputData1 = R1;
				//dirrOutput1 <= R1[7:5];
			end
			
			'b010: begin
				outputData1 = R2;
				//dirrOutput1 <= R2[7:5];
			end
			
			'b011: begin
				outputData1 = R3;
				//dirrOutput1 <= R3[7:5];
			end
			
			'b100: begin
				outputData1 = R4;
				//dirrOutput1 <= R4[7:5];
			end
			
			'b101: begin
				outputData1 = R5;
				//dirrOutput1 <= R5[7:5];
			end
			
			'b110: begin
				outputData1 = R6;
				//dirrOutput1 <= R6[7:5];
			end
			
			'b111: begin
				outputData1 = R7;
				//dirrOutput1 <= R7[7:5];
			end
			
			default: begin
				//default case
			end
		endcase	
	end
	
	//para sacar un segundo elemento del arreglo de registros
	always @(dirrOutput2) begin
		case (dirrOutput2)
			'b000: begin
				outputData2 = R0;
				//dirrOutput1 <= R0[7:5];
			end
			
			'b001: begin
				outputData2 = R1;
				//dirrOutput1 <= R1[7:5];
			end
			
			'b010: begin
				outputData2 = R2;
				//dirrOutput1 <= R2[7:5];
			end
			
			'b011: begin
				outputData2 = R3;
				//dirrOutput1 <= R3[7:5];
			end
			
			'b100: begin
				outputData2 = R4;
				//dirrOutput1 <= R4[7:5];
			end
			
			'b101: begin
				outputData2 = R5;
				//dirrOutput1 <= R5[7:5];
			end
			
			'b110: begin
				outputData2 = R6;
				//dirrOutput1 <= R6[7:5];
			end
			
			'b111: begin
				outputData2 = R7;
				//dirrOutput1 <= R7[7:5];
			end
			
			default: begin
				//default case
			end
		endcase	
	end
	
	//para sacar un segundo elemento del arreglo de registros
	/*always @(dirrOutput2) begin
		case (dirrInput)
			'b000: begin
				//code
			end
			
			'b001: begin
				//code
			end
			
			'b010: begin
				//code
			end
			
			'b011: begin
				//code
			end
			
			'b100: begin
				//code
			end
			
			'b101: begin
				//code
			end
			
			'b110: begin
				//code
			end
			
			'b111: begin
				//code
			end
			
			default: begin
				//code
			end
		endcase	
	end*/
	//WE WILL USE A SWITCH FOR EVERY CASE OF DIRR OUTPUT
	
	
	//parameter BITS_DATA = 32;
	//parameter BITS_ADDR = 16;
	
	//output [BITS_DATA-1:0] dataOutput;
	//wire dataOutput;
	//output [BITS_ADDR-1:0] dirrOutput;
	//wire dirrOutput;
	//input [BITS_DATA-1:0] dataInput;
	//wire dataInput;
//	reg dataInput, dataOutput, dirrOutput;
	
	//reg [BITS_DATA-1:0] contentRegister;
	
	//always @ (dataInput) begin
		//contentRegister = dataInput;
		//dirrOutput = contentRegister[16:BITS_DATA-1];
		//dataOutput = dataInput;
//	end
	
endmodule

registros_tb.v
/*******************************
Universidad de Costa Rica
CI-0114: Fundamentos de Arquitectura

Circuito de prueba para el circuito registro.v
*********************************/

`timescale 1us/100ns

module Register_tb;
	//reg [31:0] data_Output;
	//reg  [31:0] data_Input;
	//reg  [2:0] dirr;
	
	reg [31:0] _inputData;
	reg [2:0] _dirrInput;
	reg [2:0] _dirrOutput1;
	reg [2:0] _dirrOutput2;
	//reg [31:0] _outputData1;
	//reg [31:0] _outputData2;
	wire [31:0] _outputData1;
	wire [31:0] _outputData2;
  
	initial begin
		$dumpfile("registros.vcd");
		$dumpvars;
		// en 1 registor cabe 32bits, lo cual son 4 bytes, y por lo tanto 4 char
		
		//monitor instruction para saber por donde vamos en el arra
		$monitor("\n_inputData : %b \n_dirrInput : %b \n_dirrOutput1 : %b \n_dirrOutput2 : %b \n_outputData1 : %b \n_outputData2 : %b \n\n###############################################", _inputData, _dirrInput, _dirrOutput1, _dirrOutput2, _outputData1, _outputData2);
		
		#1 _inputData = 'hACED_CAFE; _dirrInput = 'b000;
		#1 _dirrOutput1 = 'b000;
		#1 _inputData = 'hDEAD_BEEF; _dirrInput = 'b011;
		#1 _dirrOutput1 = 'b010;
		#1 _inputData = 'hDEAD_BEEF; _dirrInput = 'b111;
		#1 _dirrOutput1 = 'b111;
		#1 _dirrOutput1 = 'b011;
		#1 _dirrOutput1 = 'b000;
		//10101100111011011100101011111110
		//clk = 1; escribir = 0;
		//#1 dirr = 'b000; data_Input = 'hACED_CAFE; 
		//direccion = 4; escribir = 1;
		//#1 data_Input <= 'hHOLA;  
		//#1 data_Input = 'hACED_CAFE;
		//#1 data_Input = 'hDEAD_BEEF;
		#1 $finish;
		//#1 escribir = 0;
		//#1 direccion = 3; data_entrada = 'hDEAD_BEEF;
		//#6 $finish;
	end
	
	registersArray registro(_inputData, _dirrInput, _dirrOutput1, _dirrOutput2, _outputData1, _outputData2);
	//registersArray registro(
	//registersArray registro();
	//Mem_D32b_A16b mem(.data_out(data_salida),.data_in(data_entrada),.address(direccion),.write(escribir),.clk(clk));
endmodule

registros.vcd
$date
	Mon Jun 13 18:42:07 2022
$end
$version
	Icarus Verilog
$end
$timescale
	100ns
$end
$scope module Register_tb $end
$var wire 32 ! _outputData2 [31:0] $end
$var wire 32 " _outputData1 [31:0] $end
$var reg 3 # _dirrInput [2:0] $end
$var reg 3 $ _dirrOutput1 [2:0] $end
$var reg 3 % _dirrOutput2 [2:0] $end
$var reg 32 & _inputData [31:0] $end
$scope module registro $end
$var wire 3 ' dirrInput [2:0] $end
$var wire 3 ( dirrOutput1 [2:0] $end
$var wire 3 ) dirrOutput2 [2:0] $end
$var wire 32 * inputData [31:0] $end
$var reg 32 + R0 [31:0] $end
$var reg 32 , R1 [31:0] $end
$var reg 32 - R2 [31:0] $end
$var reg 32 . R3 [31:0] $end
$var reg 32 / R4 [31:0] $end
$var reg 32 0 R5 [31:0] $end
$var reg 32 1 R6 [31:0] $end
$var reg 32 2 R7 [31:0] $end
$var reg 32 3 outputData1 [31:0] $end
$var reg 32 4 outputData2 [31:0] $end
$upscope $end
$upscope $end
$enddefinitions $end
#0
$dumpvars
bx 4
bx 3
bx 2
bx 1
bx 0
bx /
bx .
bx -
bx ,
bx +
bx *
bx )
bx (
bx '
bx &
bx %
bx $
bx #
bx "
bx !
$end
#10
b10101100111011011100101011111110 +
b0 #
b0 '
b10101100111011011100101011111110 &
b10101100111011011100101011111110 *
#20
b10101100111011011100101011111110 "
b10101100111011011100101011111110 3
b0 $
b0 (
#30
b11011110101011011011111011101111 .
b11 #
b11 '
b11011110101011011011111011101111 &
b11011110101011011011111011101111 *
#40
bx "
bx 3
b10 $
b10 (
#50
b11011110101011011011111011101111 2
b111 #
b111 '
#60
b11011110101011011011111011101111 "
b11011110101011011011111011101111 3
b111 $
b111 (
#70
b11 $
b11 (
#80
b10101100111011011100101011111110 "
b10101100111011011100101011111110 3
b0 $
b0 (
